mcp_info/main.py
mcp_info-0.1.0.dist-info/METADATA
mcp_info-0.1.0.dist-info/WHEEL
mcp_info-0.1.0.dist-info/entry_points.txt
mcp_info-0.1.0.dist-info/RECORD
