Metadata-Version: 2.4
Name: mcp-info
Version: 0.1.0
Summary: CLI tool to provide information about an MCP server
Author-email: Darius Schaub <schaub.darius@gmail.com>
License-Expression: BSD-3-Clause
Requires-Python: >=3.11
Requires-Dist: fastmcp>=2.12.4
Requires-Dist: rich
